zuora_sdk/__init__.py
zuora_sdk/api_client.py
zuora_sdk/api_response.py
zuora_sdk/configuration.py
zuora_sdk/exceptions.py
zuora_sdk/py.typed
zuora_sdk/rest.py
zuora_sdk/zuora_client.py
zuora_sdk/api/__init__.py
zuora_sdk/api/accounting_codes_api.py
zuora_sdk/api/accounting_periods_api.py
zuora_sdk/api/accounts_api.py
zuora_sdk/api/actions_api.py
zuora_sdk/api/adjustments_api.py
zuora_sdk/api/aggregate_queries_api.py
zuora_sdk/api/api_health_api.py
zuora_sdk/api/attachments_api.py
zuora_sdk/api/bill_run_api.py
zuora_sdk/api/bill_run_health_api.py
zuora_sdk/api/billing_documents_api.py
zuora_sdk/api/billing_preview_run_api.py
zuora_sdk/api/booking_date_backfill_job_api.py
zuora_sdk/api/catalog_groups_api.py
zuora_sdk/api/contact_snapshots_api.py
zuora_sdk/api/contacts_api.py
zuora_sdk/api/credit_memos_api.py
zuora_sdk/api/custom_event_triggers_api.py
zuora_sdk/api/custom_exchange_rates_api.py
zuora_sdk/api/custom_object_definitions_api.py
zuora_sdk/api/custom_object_jobs_api.py
zuora_sdk/api/custom_object_records_api.py
zuora_sdk/api/custom_payment_method_types_api.py
zuora_sdk/api/custom_scheduled_events_api.py
zuora_sdk/api/data_backfill_job_api.py
zuora_sdk/api/data_labeling_api.py
zuora_sdk/api/data_queries_api.py
zuora_sdk/api/debit_memos_api.py
zuora_sdk/api/deployment_api.py
zuora_sdk/api/deployment_configuration_templates_api.py
zuora_sdk/api/describe_api.py
zuora_sdk/api/e_invoicing_api.py
zuora_sdk/api/electronic_payments_health_api.py
zuora_sdk/api/files_api.py
zuora_sdk/api/fulfillments_api.py
zuora_sdk/api/hosted_pages_api.py
zuora_sdk/api/imports_api.py
zuora_sdk/api/invoice_schedules_api.py
zuora_sdk/api/invoices_api.py
zuora_sdk/api/journal_runs_api.py
zuora_sdk/api/mass_updater_api.py
zuora_sdk/api/notifications_api.py
zuora_sdk/api/o_auth_api.py
zuora_sdk/api/object_queries_api.py
zuora_sdk/api/omni_channel_subscriptions_api.py
zuora_sdk/api/operations_api.py
zuora_sdk/api/order_actions_api.py
zuora_sdk/api/order_line_items_api.py
zuora_sdk-3.13.0.dist-info/METADATA
zuora_sdk-3.13.0.dist-info/WHEEL
zuora_sdk-3.13.0.dist-info/top_level.txt
zuora_sdk-3.13.0.dist-info/RECORD
