Metadata-Version: 2.4
Name: zuora_sdk
Version: 3.13.0
Summary: Zuora API Reference
Home-page: 
Author: Zuora
Author-email: docs@zuora.com
License: MIT
Keywords: Zuora,SDK
Requires-Dist: urllib3<2.1.0,>=1.25.3
Requires-Dist: python-dateutil
Requires-Dist: pydantic<3,>=2.6
Requires-Dist: typing-extensions>=4.7.1
Requires-Dist: certifi~=2023.11.17
Dynamic: author
Dynamic: author-email
Dynamic: description
Dynamic: description-content-type
Dynamic: keywords
Dynamic: license
Dynamic: requires-dist
Dynamic: summary
